README.md
setup.py
sort_dataframeby_monthorweek/__init__.py
sort_dataframeby_monthorweek/maincode.py
sort_dataframeby_monthorweek.egg-info/PKG-INFO
sort_dataframeby_monthorweek.egg-info/SOURCES.txt
sort_dataframeby_monthorweek.egg-info/dependency_links.txt
sort_dataframeby_monthorweek.egg-info/top_level.txt