Metadata-Version: 2.1
Name: sort-dataframeby-monthorweek
Version: 0.3
Summary: Sort a dataframe by month name or by weekday name in chronological order
Home-page: https://github.com/ydineshy225/sort-dataframeby-monthorweek
Author: Yeddu Dinesh Babu
Author-email: ydineshy225@gmail.com
License: UNKNOWN
Platform: UNKNOWN
Classifier: Programming Language :: Python :: 3
Classifier: License :: OSI Approved :: MIT License
Classifier: Operating System :: OS Independent
